[{
    "id": 1,
    "firstName": "Eoan",
    "lastName": "Johlast",
    "phone": "086 346 2222",
    "company":"good compent",
    "project": "good project",
    "notes": "notes"
},
{
    "id": 2,
    "firstName": "Joseph",
    "lastName": "Kiwi",
    "phone": "086 346 2222",
    "company":"uber",
    "project": "good project",
    "notes": "notes"
},
{
    "id": 3,
    "firstName": "Ulty",
    "lastName": "MacD",
    "phone": "086 346 2222",
    "company":"iadt",
    "project": "good project",
    "notes": "notes"
},
{
    "id": 4,
    "firstName": "Rosalean",
    "lastName": "Exper",
    "phone": "086 346 2222",
    "company":"locker room",
    "project": "good project",
    "notes": "notes"
}]